riegocloud/__init__.py
riegocloud/app.py
riegocloud/db.py
riegocloud/ssh.py
riegocloud/apache/apache.conf.tpl
riegocloud/migrations/20210221_01_initialization.py
riegocloud/migrations/__init__.py
riegocloud/nginx/nginx.conf.tpl
riegocloud/web/__init__.py
riegocloud/web/security.py
riegocloud/web/static/favicon.png
riegocloud/web/static/navbar-top-fixed.css
riegocloud/web/static/reset.css
riegocloud/web/static/vendor/bootstrap.bundle.min.js
riegocloud/web/static/vendor/bootstrap.bundle.min.js.map
riegocloud/web/static/vendor/bootstrap.min.css
riegocloud/web/static/vendor/bootstrap.min.css.map
riegocloud/web/templates/base.html
riegocloud/web/templates/clients/edit.html
riegocloud/web/templates/clients/index.html
riegocloud/web/templates/clients/new.html
riegocloud/web/templates/clients/view.html
riegocloud/web/templates/home/index.html
riegocloud/web/templates/security/login.html
riegocloud/web/templates/security/profile.html
riegocloud/web/templates/system/index.html
riegocloud/web/templates/users/edit.html
riegocloud/web/templates/users/index.html
riegocloud/web/templates/users/new.html
riegocloud/web/templates/users/view.html
riegocloud/web/views/__init__.py
riegocloud/web/views/api.py
riegocloud/web/views/clients.py
riegocloud/web/views/home.py
riegocloud/web/views/system.py
riegocloud/web/views/users.py
riegocloud-0.1.31.data/scripts/setup_service.sh
riegocloud-0.1.31.dist-info/LICENSE
riegocloud-0.1.31.dist-info/METADATA
riegocloud-0.1.31.dist-info/WHEEL
riegocloud-0.1.31.dist-info/entry_points.txt
riegocloud-0.1.31.dist-info/top_level.txt
riegocloud-0.1.31.dist-info/RECORD
