Metadata-Version: 2.1
Name: riegocloud
Version: 0.1.31
Summary: Riego Cloud Service
Home-page: https://github.com/py-steph/riegocloud
Author: Stephan Winter
Author-email: riego@finca-panorama.es
License: UNKNOWN
Platform: UNKNOWN
Classifier: Programming Language :: Python :: 3.7
Classifier: Programming Language :: Python :: 3.8
Classifier: Programming Language :: Python :: 3.9
Classifier: License :: OSI Approved :: MIT License
Classifier: Development Status :: 3 - Alpha
Classifier: Framework :: AsyncIO
Classifier: Operating System :: POSIX :: Linux
Requires-Python: >=3.7
License-File: LICENSE
Requires-Dist: ConfigArgParse
Requires-Dist: aiohttp
Requires-Dist: aiohttp-jinja2
Requires-Dist: aiohttp-session[secure]
Requires-Dist: aiohttp-debugtoolbar
Requires-Dist: yoyo-migrations
Requires-Dist: bcrypt
Requires-Dist: cchardet
Requires-Dist: asyncssh
Requires-Dist: aiomysql
Requires-Dist: uvloop ; sys_platform != "win32"
